influx_line_protocol/__init__.py
influx_line_protocol/metric.py
influx_line_protocol/metric_collection.py
influx_line_protocol/test_metric.py
influx_line_protocol/test_metric_collection.py
influx_line_protocol-0.1.5.dist-info/LICENSE
influx_line_protocol-0.1.5.dist-info/METADATA
influx_line_protocol-0.1.5.dist-info/WHEEL
influx_line_protocol-0.1.5.dist-info/top_level.txt
influx_line_protocol-0.1.5.dist-info/RECORD
