Metadata-Version: 2.1
Name: influx-line-protocol
Version: 0.1.5
Summary: Implementation of influxdata line protocol format in python
Home-page: https://github.com/SebastianCzoch/influx-line-protocol
Author: Sebastian Czoch
Author-email: sebastian@czoch.pl
License: MIT
Classifier: Development Status :: 4 - Beta
Classifier: Intended Audience :: System Administrators
Classifier: License :: OSI Approved :: MIT License
Classifier: Programming Language :: Python :: 2
Classifier: Operating System :: OS Independent
License-File: LICENSE
